chiklisp_builder.py
chiklisp_builder-0.1.2.dist-info/LICENSE
chiklisp_builder-0.1.2.dist-info/METADATA
chiklisp_builder-0.1.2.dist-info/WHEEL
chiklisp_builder-0.1.2.dist-info/top_level.txt
chiklisp_builder-0.1.2.dist-info/RECORD
