Metadata-Version: 2.1
Name: chiklisp-builder
Version: 0.1.2
Summary: Allow on-demand builds of chiklisp with recursive dependency checking.
Author-email: Richard Kiss <him@richardkiss.com>
License: Copyright 2023 by Richard Kiss
License-File: LICENSE
Requires-Dist: klvm-tools-rs
Requires-Dist: runtime-builder >=0.1.3
